{"devices":[{"deviceID":"FEFEAE26","thingUID":"Device_FEFEAE26"},{"deviceID":"FEFEAE26","thingUID":"Device_FEFEAE26"},{"deviceID":"FEFEAE26","thingUID":"Device_FEFEAE26"},{"deviceID":"FEFEAE26","thingUID":"Device_FEFEAE26"},{"deviceID":"0193EFFD","thingUID":"Device_0193EFFD"},{"deviceID":"0193EFFD","thingUID":"Device_0193EFFD"},{"deviceID":"0193EFFD","thingUID":"Device_0193EFFD"},{"deviceID":"0193EFFD","thingUID":"Device_0193EFFD"},{"deviceID":"01852BA6","thingUID":"Device_01852BA6"},{"deviceID":"FEFEAE26","thingUID":"Device_FEFEAE26"},{"deviceID":"01852BA6","thingUID":"Device_01852BA6"},{"deviceID":"0193EFFD","thingUID":"Device_0193EFFD"},{"deviceID":"FEFEAE26","thingUID":"Device_FEFEAE26"},{"deviceID":"FFA9FF00","thingUID":"enoceanBridge"},{"deviceID":"01872C13","thingUID":"AfrisoCO2"}]}